bsl_universal/__init__.py
bsl_universal/test.py
bsl_universal/analysis/__init__.py
bsl_universal/analysis/_mantisCam/__init__.py
bsl_universal/analysis/_mantisCam/mantis_file.py
bsl_universal/analysis/_mantisCam/mantis_file_GS.py
bsl_universal/analysis/_mantisCam/mantis_folder.py
bsl_universal/analysis/_mantisCam/mantis_folder_GS.py
bsl_universal/instruments/__init__.py
bsl_universal/instruments/inst.py
bsl_universal/instruments/_inst_lib/__init__.py
bsl_universal/instruments/_inst_lib/headers/__init__.py
bsl_universal/instruments/_inst_lib/headers/_bsl_inst_info.py
bsl_universal/instruments/_inst_lib/headers/_bsl_inst_info_class.py
bsl_universal/instruments/_inst_lib/headers/_bsl_logger.py
bsl_universal/instruments/_inst_lib/headers/_bsl_type.py
bsl_universal/instruments/_inst_lib/instruments/_BSC203.py
bsl_universal/instruments/_inst_lib/instruments/_CS260B.py
bsl_universal/instruments/_inst_lib/instruments/_DC2200.py
bsl_universal/instruments/_inst_lib/instruments/_Futek_USB_520.py
bsl_universal/instruments/_inst_lib/instruments/_HR4000CG.py
bsl_universal/instruments/_inst_lib/instruments/_M69920.py
bsl_universal/instruments/_inst_lib/instruments/_PM100D.py
bsl_universal/instruments/_inst_lib/instruments/_PM400.py
bsl_universal/instruments/_inst_lib/instruments/_RS_7_1.py
bsl_universal/instruments/_inst_lib/instruments/_SP_2150.py
bsl_universal/instruments/_inst_lib/instruments/__init__.py
bsl_universal/instruments/_inst_lib/instruments/_mantisCam.py
bsl_universal/instruments/_inst_lib/instruments/_thorlabs_apt_device/__init__.py
bsl_universal/instruments/_inst_lib/instruments/_thorlabs_apt_device/enums.py
bsl_universal/instruments/_inst_lib/instruments/_thorlabs_apt_device/utils.py
bsl_universal/instruments/_inst_lib/instruments/_thorlabs_apt_device/devices/__init__.py
bsl_universal/instruments/_inst_lib/instruments/_thorlabs_apt_device/devices/aptdevice.py
bsl_universal/instruments/_inst_lib/instruments/_thorlabs_apt_device/devices/aptdevice_motor.py
bsl_universal-0.5.dist-info/licenses/LICENSE
bsl_universal-0.5.dist-info/METADATA
bsl_universal-0.5.dist-info/WHEEL
bsl_universal-0.5.dist-info/top_level.txt
bsl_universal-0.5.dist-info/RECORD
