Metadata-Version: 2.4
Name: bsl_universal
Version: 0.5
Summary: Universal Research Library for BioSensors Lab @ UIUC
Home-page: https://github.com/BioSensorsLab-Illinois/bsl_universal
Download-URL: https://github.com/BioSensorsLab-Illinois/bsl_universal/archive/refs/tags/Testing.tar.gz
Author: Zhongmin Zhu
Author-email: j@metadata.cc
License: MIT
Keywords: BSL,Instrument,UIUC
Classifier: Development Status :: 3 - Alpha
Classifier: Intended Audience :: Developers
Classifier: Topic :: Software Development :: Build Tools
Classifier: License :: OSI Approved :: MIT License
Classifier: Programming Language :: Python :: 3
Classifier: Programming Language :: Python :: 3.8
Classifier: Programming Language :: Python :: 3.9
Classifier: Programming Language :: Python :: 3.10
Classifier: Programming Language :: Python :: 3.11
License-File: LICENSE
Requires-Dist: loguru>=0.6.0
Requires-Dist: numpy>=1.22.0
Requires-Dist: pyserial>=3.5
Requires-Dist: pyvisa>=1.11.3
Requires-Dist: pyvisa-py>=0.5.2
Requires-Dist: seabreeze>=2.0.2
Requires-Dist: libusb>=1.0.24b3
Requires-Dist: pycolorname>=0.1.0
Requires-Dist: scikit-image>=0.19.2
Requires-Dist: tqdm>=4.62.3
Requires-Dist: h5py>=3.0.0
Requires-Dist: opencv-python>=4.5.0
Requires-Dist: pyzmq>=22.0.0
Dynamic: author
Dynamic: author-email
Dynamic: classifier
Dynamic: download-url
Dynamic: home-page
Dynamic: keywords
Dynamic: license
Dynamic: license-file
Dynamic: requires-dist
Dynamic: summary
